annotell_auth-2.0.1-py3.8-nspkg.pth
annotell/auth/__init__.py
annotell/auth/authsession.py
annotell/auth/credentials_parser.py
annotell/auth/base/__init__.py
annotell/auth/base/auth_client.py
annotell/auth/base/refresh_expiry_fix.py
annotell/auth/httpx/__init__.py
annotell/auth/httpx/async_client.py
annotell/auth/requests/__init__.py
annotell/auth/requests/auth_session.py
annotell_auth-2.0.1.dist-info/METADATA
annotell_auth-2.0.1.dist-info/WHEEL
annotell_auth-2.0.1.dist-info/namespace_packages.txt
annotell_auth-2.0.1.dist-info/top_level.txt
annotell_auth-2.0.1.dist-info/RECORD
