Metadata-Version: 2.1
Name: annotell-auth
Version: 2.0.1
Summary: Annotell Authentication
Home-page: https://github.com/annotell/annotell-python
Download-URL: https://github.com/annotell/annotell-python/tarball/2.0.1
Author: Annotell
Author-email: Michel Edkrantz <michel.edkrantz@annotell.com>
License: MIT
Keywords: API,Annotell
Platform: UNKNOWN
Classifier: Development Status :: 5 - Production/Stable
Classifier: License :: OSI Approved :: MIT License
Classifier: Intended Audience :: Developers
Classifier: Programming Language :: Python :: 3
Requires-Python: ~=3.6
Requires-Dist: authlib (<1.1,>=0.14.1)
Provides-Extra: full
Requires-Dist: requests (<3,>=2.20) ; extra == 'full'
Requires-Dist: httpx (<1,>=0.20) ; extra == 'full'
Provides-Extra: httpx
Requires-Dist: httpx (<1,>=0.20) ; extra == 'httpx'
Provides-Extra: requests
Requires-Dist: requests (<3,>=2.20) ; extra == 'requests'
